geoclide/__init__.py
geoclide/advancedvecope.py
geoclide/basic.py
geoclide/constante.py
geoclide/intersection.py
geoclide/mathope.py
geoclide/quadrics.py
geoclide/shapes.py
geoclide/transform.py
geoclide/trianglemesh.py
geoclide/vecope.py
geoclide/img/annulus.png
geoclide/img/disk.png
geoclide/img/geoclide_logo2.png
geoclide/img/oblate.png
geoclide/img/partial_annulus.png
geoclide/img/prolate.png
geoclide/img/sphere.png
geoclide/img/sphere_partial1.png
geoclide/img/sphere_partial2.png
geoclide/tests/__init__.py
geoclide/tests/test_advancedvecope.py
geoclide/tests/test_basic.py
geoclide/tests/test_mathope.py
geoclide/tests/test_quadrics.py
geoclide/tests/test_transform.py
geoclide/tests/test_trianglemesh.py
geoclide/tests/test_vecope.py
geoclide/tests/data/annulus_partial_r1_ir0p5_reso27_phimax270.gcnc
geoclide/tests/data/annulus_r1_ir0p5_reso36.gcnc
geoclide/tests/data/disk_r1_reso36.gcnc
geoclide/tests/data/disk_r1_zh5_reso36.gcnc
geoclide/tests/data/oblate_rxy1p5_rz1p2_resth18_resph36.gcnc
geoclide/tests/data/prolate_rxy1p5_rz3_resth18_resph36.gcnc
geoclide/tests/data/sphere_r1p5_resth18_resph18_phimax180.gcnc
geoclide/tests/data/sphere_r1p5_resth18_resph36.gcnc
geoclide-3.0.3.dist-info/licenses/LICENSE.txt
geoclide-3.0.3.dist-info/METADATA
geoclide-3.0.3.dist-info/WHEEL
geoclide-3.0.3.dist-info/top_level.txt
geoclide-3.0.3.dist-info/RECORD
