Metadata-Version: 2.4
Name: geoclide
Version: 3.0.3
Summary: A python package for geometric calculations in the three-dimentional Euclidian space
Author-email: Mustapha Moulana <mm@hygeos.com>
License: 
Project-URL: Homepage, https://hygeos.github.io/geoclide/
Project-URL: Source, https://github.com/hygeos/geoclide
Classifier: Development Status :: 5 - Production/Stable
Classifier: License :: Free for non-commercial use
Classifier: License :: Other/Proprietary License
Classifier: Intended Audience :: Science/Research
Classifier: Intended Audience :: Developers
Classifier: Programming Language :: Python
Classifier: Programming Language :: Python :: 3
Classifier: Programming Language :: Python :: 3.8
Classifier: Programming Language :: Python :: 3.9
Classifier: Programming Language :: Python :: 3.10
Classifier: Programming Language :: Python :: 3.11
Classifier: Programming Language :: Python :: 3.12
Classifier: Programming Language :: Python :: 3.13
Classifier: Topic :: Scientific/Engineering
Requires-Python: >=3.8
License-File: LICENSE.txt
Requires-Dist: numpy
Requires-Dist: xarray
Requires-Dist: pytest
Requires-Dist: matplotlib
Requires-Dist: ipympl
Requires-Dist: ipykernel
Requires-Dist: netcdf4
Requires-Dist: trimesh
Dynamic: license-file
